{
  "settings": {
    "migrated": 6,
    "iconPacksPath": ".obsidian/icons",
    "fontSize": 16,
    "emojiStyle": "native",
    "iconColor": null,
    "recentlyUsedIcons": [
      "LiAnchor",
      "LiAntenna",
      "LiArchive",
      "LiAccessibility",
      "LiAlarmClockCheck"
    ],
    "recentlyUsedIconsSize": 5,
    "rules": [],
    "extraMargin": {
      "top": 0,
      "right": 4,
      "bottom": 0,
      "left": 0
    },
    "iconInTabsEnabled": false,
    "iconInTitleEnabled": false,
    "iconInTitlePosition": "above",
    "iconInFrontmatterEnabled": false,
    "iconInFrontmatterFieldName": "icon",
    "iconColorInFrontmatterFieldName": "iconColor",
    "iconsBackgroundCheckEnabled": false,
    "iconsInNotesEnabled": true,
    "iconsInLinksEnabled": true,
    "iconIdentifier": ":",
    "lucideIconPackType": "native",
    "debugMode": false,
    "useInternalPlugins": false
  },
  "COMANDS UTILS": {
    "iconName": "LiArchive",
    "iconColor": "#010693"
  },
  "DAILY": {
    "iconName": "LiAlarmClockCheck",
    "iconColor": "#8201b2"
  },
  "DAILY/task's.md": "LiAccessibility",
  "DAILY/notes": "LiAlarmClockCheck",
  "DEV/desenvolvimento_web": "LiAnchor",
  "DEV/desenvolvimento_web/desenvolvimento_web.canvas": "LiAntenna",
  "DEV/desenvolvimento_web/docs": "LiAsterisk",
  "DEV/desenvolvimento_web/images": "LiAperture",
  "DEV/desenvolvimento_web/docs/architecture_patterns_doc.md": "LiAsteriskSquare",
  "DEV/desenvolvimento_web/docs/desenvolvimento_web_doc.md": "LiAsterisk",
  "DEV/desenvolvimento_web/docs/design_patterns_doc.md": "LiAsteriskSquare",
  "DEV": {
    "iconName": "LiAnchor",
    "iconColor": "#c22424"
  },
  "DEV/RPA": "LiAnchor"
}